yshs/__init__.py
yshs/version.py
yshs/apis/__init__.py
yshs/apis/models.py
yshs/apis/users.py
yshs/worker_api/__init__.py
yshs/worker_api/chat.py
yshs/worker_api/chat_thread.py
yshs/worker_api/client.py
yshs-1.1.0.dist-info/METADATA
yshs-1.1.0.dist-info/WHEEL
yshs-1.1.0.dist-info/top_level.txt
yshs-1.1.0.dist-info/RECORD
