Metadata-Version: 2.1
Name: yshs
Version: 1.1.0
Summary: The open-source yshs library.
Home-page: https://github.com/zfy0216/open-yshs
Author: Feiyan Zhang
Author-email: zhangfy0216@gmail.com
License: MIT
Classifier: License :: OSI Approved :: MIT License
Classifier: Programming Language :: Python
Classifier: Programming Language :: Python :: 3
Classifier: Programming Language :: Python :: 3.8
Classifier: Programming Language :: Python :: 3.9
Classifier: Programming Language :: Python :: 3.10
Classifier: Programming Language :: Python :: 3.11
Classifier: Programming Language :: Python :: 3.12
Classifier: Programming Language :: Python :: Implementation :: CPython
Classifier: Programming Language :: Python :: Implementation :: PyPy
Requires-Python: >=3.8.0
Requires-Dist: requests
